{
    "name": "Echo AI Dev Container",
    "dockerComposeFile": "../docker-compose.yml",
    "service": "app",
    "workspaceFolder": "/app",
    "customizations": {
        "vscode": {
            "extensions": [
                "dbaeumer.vscode-eslint",
                "bradlc.vscode-tailwindcss",
                "GitHub.copilot",
                "GitHub.copilot-chat",
                "esbenp.prettier-vscode"
            ]
        }
    },
    "remoteEnv": {
        "NODE_ENV": "development"
    }
}